odoo/addons/product_secondary_unit/README.rst
odoo/addons/product_secondary_unit/__init__.py
odoo/addons/product_secondary_unit/__manifest__.py
odoo/addons/product_secondary_unit/i18n/es.po
odoo/addons/product_secondary_unit/i18n/fr.po
odoo/addons/product_secondary_unit/i18n/it.po
odoo/addons/product_secondary_unit/i18n/product_secondary_unit.pot
odoo/addons/product_secondary_unit/migrations/11.0.1.0.2/post-migration.py
odoo/addons/product_secondary_unit/models/__init__.py
odoo/addons/product_secondary_unit/models/product_second_unit.py
odoo/addons/product_secondary_unit/models/product_template.py
odoo/addons/product_secondary_unit/readme/CONTRIBUTORS.rst
odoo/addons/product_secondary_unit/readme/DESCRIPTION.rst
odoo/addons/product_secondary_unit/readme/USAGE.rst
odoo/addons/product_secondary_unit/security/ir.model.access.csv
odoo/addons/product_secondary_unit/security/security.xml
odoo/addons/product_secondary_unit/static/description/icon.png
odoo/addons/product_secondary_unit/static/description/index.html
odoo/addons/product_secondary_unit/tests/__init__.py
odoo/addons/product_secondary_unit/tests/test_product_second_unit.py
odoo/addons/product_secondary_unit/views/product_views.xml
odoo11_addon_product_secondary_unit-11.0.1.0.2.99.dev12.dist-info/METADATA
odoo11_addon_product_secondary_unit-11.0.1.0.2.99.dev12.dist-info/WHEEL
odoo11_addon_product_secondary_unit-11.0.1.0.2.99.dev12.dist-info/top_level.txt
odoo11_addon_product_secondary_unit-11.0.1.0.2.99.dev12.dist-info/RECORD
